change_proc_priority/README.MD
change_proc_priority/__init__.py
change_proc_priority/requirements.txt
change_proc_priority/thirdparty.json
change_proc_priority-0.10.dist-info/LICENSE.rst
change_proc_priority-0.10.dist-info/METADATA
change_proc_priority-0.10.dist-info/WHEEL
change_proc_priority-0.10.dist-info/top_level.txt
change_proc_priority-0.10.dist-info/RECORD
