Metadata-Version: 2.1
Name: change-proc-priority
Version: 0.10
Summary: Constantly checks and changes the priority of processes based on the provided parameters - Windows only
Home-page: https://github.com/hansalemaos/change_proc_priority
Author: Johannes Fischer
Author-email: aulasparticularesdealemaosp@gmail.com
License: MIT
Keywords: priority,processes
Classifier: Development Status :: 4 - Beta
Classifier: Programming Language :: Python :: 3 :: Only
Classifier: Programming Language :: Python :: 3.10
Classifier: Topic :: Software Development :: Libraries :: Python Modules
Classifier: Topic :: Utilities
License-File: LICENSE.rst
Requires-Dist: ctrlchandler
Requires-Dist: ctypes-window-info
Requires-Dist: hackyargparser
Requires-Dist: kthread
Requires-Dist: kthread-sleep
Requires-Dist: psutil
